{
  "learners":
  [
    {
	  "name":"Allen",
	  "password":"123456",
	  "image":"allen.png"
	},
	{
	  "name":"Barbara",
	  "password":"123456",
	  "image":"barbara.png"
	},
	{
	  "name":"Carol",
	  "password":"123456",
	  "image":"carol.png"
	},
	{
	  "name":"Steve",
	  "password":"123456",
	  "image":"steve.png"
	},
	{
	  "name":"Jerry",
	  "password":"123456",
	  "image":"jerry.png"
	},
	{
	  "name":"Helen",
	  "password":"123456",
	  "image":"helen.png"
	},
	{
	  "name":"Tom",
	  "password":"123456",
	  "image":"tom.png"
	},
	{
	  "name":"Lily",
	  "password":"123456",
	  "image":"lily.png"
	},
	{
	  "name":"Mike",
	  "password":"123456",
	  "image":"mike.png"
	},
	{
	  "name":"Allen",
	  "password":"123456",
	  "image":"allen.png"
	},
	{
	  "name":"Kate",
	  "password":"123456",
	  "image":"kate.png"
	},
	{
	  "name":"Tim",
	  "password":"123456",
	  "image":"tim.png"
	},
	{
	  "name":"Caroline",
	  "password":"123456",
	  "image":"caroline.png"
	},
	{
	  "name":"Kevin",
	  "password":"123456",
	  "image":"kevin.png"
	}
  ]
}